{
  "ListActiveMetrics": {
    "responses": {
      "200": {
        "json": {
          "from": "string",
          "metrics": "string"
        },
        "html": "\n  <div class=\" schema-table row\">\n    <div class=\"col-12 column\">\n      <div class=\"row table-header\">\n        <div class=\"col-4 field-column\">\n          <p class=\"font-semibold\">Field</p>\n        </div>\n        <div class=\"col-2 type-column\">\n          <p class=\"font-semibold\">Type</p>\n        </div>\n        <div class=\"col-6 description-column\">\n          <p class=\"font-semibold\">Description</p>\n        </div>\n      </div>\n      \n      <div class=\"row  \">\n        <div class=\"col-12 first-column\">\n          <div class=\"row first-row \">\n            \n    <div class=\"col-4 field-column\">\n      <p class=\"key\">from</p>\n    </div>\n  \n            <div class=\"col-2 type-column\"><p>string</p></div>\n            <div class=\"col-6 description-column\"><p>Time when the metrics were active, seconds since the Unix epoch.</p>\n</div>\n          </div>\n          \n        </div>\n      </div>\n      \n      <div class=\"row  \">\n        <div class=\"col-12 first-column\">\n          <div class=\"row first-row \">\n            \n    <div class=\"col-4 field-column\">\n      <p class=\"key\">metrics</p>\n    </div>\n  \n            <div class=\"col-2 type-column\"><p>[string]</p></div>\n            <div class=\"col-6 description-column\"><p>List of metric names.</p>\n</div>\n          </div>\n          \n        </div>\n      </div>\n      \n    </div>  \n  </div>"
      },
      "400": {
        "json": {
          "errors": "Bad Request"
        },
        "html": "\n  <div class=\" schema-table row\">\n    <div class=\"col-12 column\">\n      <div class=\"row table-header\">\n        <div class=\"col-4 field-column\">\n          <p class=\"font-semibold\">Field</p>\n        </div>\n        <div class=\"col-2 type-column\">\n          <p class=\"font-semibold\">Type</p>\n        </div>\n        <div class=\"col-6 description-column\">\n          <p class=\"font-semibold\">Description</p>\n        </div>\n      </div>\n      \n      <div class=\"row  \">\n        <div class=\"col-12 first-column\">\n          <div class=\"row first-row \">\n            \n    <div class=\"col-4 field-column\">\n      <p class=\"key\">errors<span style=\"color:red;\">*</span></p>\n    </div>\n  \n            <div class=\"col-2 type-column\"><p>[string]</p></div>\n            <div class=\"col-6 description-column\"></div>\n          </div>\n          \n        </div>\n      </div>\n      \n    </div>  \n  </div>"
      }
    },
    "request": {
      "json": {},
      "html": ""
    }
  },
  "GetMetricMetadata": {
    "responses": {
      "200": {
        "json": {
          "description": "string",
          "integration": "string",
          "per_unit": "second",
          "short_name": "string",
          "statsd_interval": "integer",
          "type": "count",
          "unit": "byte"
        },
        "html": "\n  <div class=\" schema-table row\">\n    <div class=\"col-12 column\">\n      <div class=\"row table-header\">\n        <div class=\"col-4 field-column\">\n          <p class=\"font-semibold\">Field</p>\n        </div>\n        <div class=\"col-2 type-column\">\n          <p class=\"font-semibold\">Type</p>\n        </div>\n        <div class=\"col-6 description-column\">\n          <p class=\"font-semibold\">Description</p>\n        </div>\n      </div>\n      \n      <div class=\"row  \">\n        <div class=\"col-12 first-column\">\n          <div class=\"row first-row \">\n            \n    <div class=\"col-4 field-column\">\n      <p class=\"key\">description</p>\n    </div>\n  \n            <div class=\"col-2 type-column\"><p>string</p></div>\n            <div class=\"col-6 description-column\"><p>Metric description.</p>\n</div>\n          </div>\n          \n        </div>\n      </div>\n      \n      <div class=\"row  \">\n        <div class=\"col-12 first-column\">\n          <div class=\"row first-row \">\n            \n    <div class=\"col-4 field-column\">\n      <p class=\"key\">integration</p>\n    </div>\n  \n            <div class=\"col-2 type-column\"><p>string <span class=\"read-only\">&#127361;</span></p></div>\n            <div class=\"col-6 description-column\"><p>Name of the integration that sent the metric if applicable.</p>\n</div>\n          </div>\n          \n        </div>\n      </div>\n      \n      <div class=\"row  \">\n        <div class=\"col-12 first-column\">\n          <div class=\"row first-row \">\n            \n    <div class=\"col-4 field-column\">\n      <p class=\"key\">per_unit</p>\n    </div>\n  \n            <div class=\"col-2 type-column\"><p>string</p></div>\n            <div class=\"col-6 description-column\"><p>Per unit of the metric such as <code>second</code> in <code>bytes per second</code>.</p>\n</div>\n          </div>\n          \n        </div>\n      </div>\n      \n      <div class=\"row  \">\n        <div class=\"col-12 first-column\">\n          <div class=\"row first-row \">\n            \n    <div class=\"col-4 field-column\">\n      <p class=\"key\">short_name</p>\n    </div>\n  \n            <div class=\"col-2 type-column\"><p>string</p></div>\n            <div class=\"col-6 description-column\"><p>A more human-readable and abbreviated version of the metric name.</p>\n</div>\n          </div>\n          \n        </div>\n      </div>\n      \n      <div class=\"row  \">\n        <div class=\"col-12 first-column\">\n          <div class=\"row first-row \">\n            \n    <div class=\"col-4 field-column\">\n      <p class=\"key\">statsd_interval</p>\n    </div>\n  \n            <div class=\"col-2 type-column\"><p>int64</p></div>\n            <div class=\"col-6 description-column\"><p>Statsd flush interval of the metric in seconds if applicable.</p>\n</div>\n          </div>\n          \n        </div>\n      </div>\n      \n      <div class=\"row  \">\n        <div class=\"col-12 first-column\">\n          <div class=\"row first-row \">\n            \n    <div class=\"col-4 field-column\">\n      <p class=\"key\">type</p>\n    </div>\n  \n            <div class=\"col-2 type-column\"><p>string</p></div>\n            <div class=\"col-6 description-column\"><p>Metric type such as <code>gauge</code> or <code>rate</code>.</p>\n</div>\n          </div>\n          \n        </div>\n      </div>\n      \n      <div class=\"row  \">\n        <div class=\"col-12 first-column\">\n          <div class=\"row first-row \">\n            \n    <div class=\"col-4 field-column\">\n      <p class=\"key\">unit</p>\n    </div>\n  \n            <div class=\"col-2 type-column\"><p>string</p></div>\n            <div class=\"col-6 description-column\"><p>Primary unit of the metric such as <code>byte</code> or <code>operation</code>.</p>\n</div>\n          </div>\n          \n        </div>\n      </div>\n      \n    </div>  \n  </div>"
      },
      "404": {
        "json": {
          "errors": "Bad Request"
        },
        "html": "\n  <div class=\" schema-table row\">\n    <div class=\"col-12 column\">\n      <div class=\"row table-header\">\n        <div class=\"col-4 field-column\">\n          <p class=\"font-semibold\">Field</p>\n        </div>\n        <div class=\"col-2 type-column\">\n          <p class=\"font-semibold\">Type</p>\n        </div>\n        <div class=\"col-6 description-column\">\n          <p class=\"font-semibold\">Description</p>\n        </div>\n      </div>\n      \n      <div class=\"row  \">\n        <div class=\"col-12 first-column\">\n          <div class=\"row first-row \">\n            \n    <div class=\"col-4 field-column\">\n      <p class=\"key\">errors<span style=\"color:red;\">*</span></p>\n    </div>\n  \n            <div class=\"col-2 type-column\"><p>[string]</p></div>\n            <div class=\"col-6 description-column\"></div>\n          </div>\n          \n        </div>\n      </div>\n      \n    </div>  \n  </div>"
      }
    },
    "request": {
      "json": {},
      "html": ""
    }
  },
  "UpdateMetricMetadata": {
    "responses": {
      "200": {
        "json": {
          "description": "string",
          "integration": "string",
          "per_unit": "second",
          "short_name": "string",
          "statsd_interval": "integer",
          "type": "count",
          "unit": "byte"
        },
        "html": "\n  <div class=\" schema-table row\">\n    <div class=\"col-12 column\">\n      <div class=\"row table-header\">\n        <div class=\"col-4 field-column\">\n          <p class=\"font-semibold\">Field</p>\n        </div>\n        <div class=\"col-2 type-column\">\n          <p class=\"font-semibold\">Type</p>\n        </div>\n        <div class=\"col-6 description-column\">\n          <p class=\"font-semibold\">Description</p>\n        </div>\n      </div>\n      \n      <div class=\"row  \">\n        <div class=\"col-12 first-column\">\n          <div class=\"row first-row \">\n            \n    <div class=\"col-4 field-column\">\n      <p class=\"key\">description</p>\n    </div>\n  \n            <div class=\"col-2 type-column\"><p>string</p></div>\n            <div class=\"col-6 description-column\"><p>Metric description.</p>\n</div>\n          </div>\n          \n        </div>\n      </div>\n      \n      <div class=\"row  \">\n        <div class=\"col-12 first-column\">\n          <div class=\"row first-row \">\n            \n    <div class=\"col-4 field-column\">\n      <p class=\"key\">integration</p>\n    </div>\n  \n            <div class=\"col-2 type-column\"><p>string <span class=\"read-only\">&#127361;</span></p></div>\n            <div class=\"col-6 description-column\"><p>Name of the integration that sent the metric if applicable.</p>\n</div>\n          </div>\n          \n        </div>\n      </div>\n      \n      <div class=\"row  \">\n        <div class=\"col-12 first-column\">\n          <div class=\"row first-row \">\n            \n    <div class=\"col-4 field-column\">\n      <p class=\"key\">per_unit</p>\n    </div>\n  \n            <div class=\"col-2 type-column\"><p>string</p></div>\n            <div class=\"col-6 description-column\"><p>Per unit of the metric such as <code>second</code> in <code>bytes per second</code>.</p>\n</div>\n          </div>\n          \n        </div>\n      </div>\n      \n      <div class=\"row  \">\n        <div class=\"col-12 first-column\">\n          <div class=\"row first-row \">\n            \n    <div class=\"col-4 field-column\">\n      <p class=\"key\">short_name</p>\n    </div>\n  \n            <div class=\"col-2 type-column\"><p>string</p></div>\n            <div class=\"col-6 description-column\"><p>A more human-readable and abbreviated version of the metric name.</p>\n</div>\n          </div>\n          \n        </div>\n      </div>\n      \n      <div class=\"row  \">\n        <div class=\"col-12 first-column\">\n          <div class=\"row first-row \">\n            \n    <div class=\"col-4 field-column\">\n      <p class=\"key\">statsd_interval</p>\n    </div>\n  \n            <div class=\"col-2 type-column\"><p>int64</p></div>\n            <div class=\"col-6 description-column\"><p>Statsd flush interval of the metric in seconds if applicable.</p>\n</div>\n          </div>\n          \n        </div>\n      </div>\n      \n      <div class=\"row  \">\n        <div class=\"col-12 first-column\">\n          <div class=\"row first-row \">\n            \n    <div class=\"col-4 field-column\">\n      <p class=\"key\">type</p>\n    </div>\n  \n            <div class=\"col-2 type-column\"><p>string</p></div>\n            <div class=\"col-6 description-column\"><p>Metric type such as <code>gauge</code> or <code>rate</code>.</p>\n</div>\n          </div>\n          \n        </div>\n      </div>\n      \n      <div class=\"row  \">\n        <div class=\"col-12 first-column\">\n          <div class=\"row first-row \">\n            \n    <div class=\"col-4 field-column\">\n      <p class=\"key\">unit</p>\n    </div>\n  \n            <div class=\"col-2 type-column\"><p>string</p></div>\n            <div class=\"col-6 description-column\"><p>Primary unit of the metric such as <code>byte</code> or <code>operation</code>.</p>\n</div>\n          </div>\n          \n        </div>\n      </div>\n      \n    </div>  \n  </div>"
      },
      "404": {
        "json": {
          "errors": "Bad Request"
        },
        "html": "\n  <div class=\" schema-table row\">\n    <div class=\"col-12 column\">\n      <div class=\"row table-header\">\n        <div class=\"col-4 field-column\">\n          <p class=\"font-semibold\">Field</p>\n        </div>\n        <div class=\"col-2 type-column\">\n          <p class=\"font-semibold\">Type</p>\n        </div>\n        <div class=\"col-6 description-column\">\n          <p class=\"font-semibold\">Description</p>\n        </div>\n      </div>\n      \n      <div class=\"row  \">\n        <div class=\"col-12 first-column\">\n          <div class=\"row first-row \">\n            \n    <div class=\"col-4 field-column\">\n      <p class=\"key\">errors<span style=\"color:red;\">*</span></p>\n    </div>\n  \n            <div class=\"col-2 type-column\"><p>[string]</p></div>\n            <div class=\"col-6 description-column\"></div>\n          </div>\n          \n        </div>\n      </div>\n      \n    </div>  \n  </div>"
      }
    },
    "request": {
      "json": {
        "description": "string",
        "integration": "string",
        "per_unit": "second",
        "short_name": "string",
        "statsd_interval": "integer",
        "type": "count",
        "unit": "byte"
      },
      "html": "\n  <div class=\" schema-table row\">\n    <div class=\"col-12 column\">\n      <div class=\"row table-header\">\n        <div class=\"col-4 field-column\">\n          <p class=\"font-semibold\">Field</p>\n        </div>\n        <div class=\"col-2 type-column\">\n          <p class=\"font-semibold\">Type</p>\n        </div>\n        <div class=\"col-6 description-column\">\n          <p class=\"font-semibold\">Description</p>\n        </div>\n      </div>\n      \n      <div class=\"row  \">\n        <div class=\"col-12 first-column\">\n          <div class=\"row first-row \">\n            \n    <div class=\"col-4 field-column\">\n      <p class=\"key\">description</p>\n    </div>\n  \n            <div class=\"col-2 type-column\"><p>string</p></div>\n            <div class=\"col-6 description-column\"><p>Metric description.</p>\n</div>\n          </div>\n          \n        </div>\n      </div>\n      \n      <div class=\"row  \">\n        <div class=\"col-12 first-column\">\n          <div class=\"row first-row \">\n            \n    <div class=\"col-4 field-column\">\n      <p class=\"key\">integration</p>\n    </div>\n  \n            <div class=\"col-2 type-column\"><p>string <span class=\"read-only\">&#127361;</span></p></div>\n            <div class=\"col-6 description-column\"><p>Name of the integration that sent the metric if applicable.</p>\n</div>\n          </div>\n          \n        </div>\n      </div>\n      \n      <div class=\"row  \">\n        <div class=\"col-12 first-column\">\n          <div class=\"row first-row \">\n            \n    <div class=\"col-4 field-column\">\n      <p class=\"key\">per_unit</p>\n    </div>\n  \n            <div class=\"col-2 type-column\"><p>string</p></div>\n            <div class=\"col-6 description-column\"><p>Per unit of the metric such as <code>second</code> in <code>bytes per second</code>.</p>\n</div>\n          </div>\n          \n        </div>\n      </div>\n      \n      <div class=\"row  \">\n        <div class=\"col-12 first-column\">\n          <div class=\"row first-row \">\n            \n    <div class=\"col-4 field-column\">\n      <p class=\"key\">short_name</p>\n    </div>\n  \n            <div class=\"col-2 type-column\"><p>string</p></div>\n            <div class=\"col-6 description-column\"><p>A more human-readable and abbreviated version of the metric name.</p>\n</div>\n          </div>\n          \n        </div>\n      </div>\n      \n      <div class=\"row  \">\n        <div class=\"col-12 first-column\">\n          <div class=\"row first-row \">\n            \n    <div class=\"col-4 field-column\">\n      <p class=\"key\">statsd_interval</p>\n    </div>\n  \n            <div class=\"col-2 type-column\"><p>int64</p></div>\n            <div class=\"col-6 description-column\"><p>Statsd flush interval of the metric in seconds if applicable.</p>\n</div>\n          </div>\n          \n        </div>\n      </div>\n      \n      <div class=\"row  \">\n        <div class=\"col-12 first-column\">\n          <div class=\"row first-row \">\n            \n    <div class=\"col-4 field-column\">\n      <p class=\"key\">type</p>\n    </div>\n  \n            <div class=\"col-2 type-column\"><p>string</p></div>\n            <div class=\"col-6 description-column\"><p>Metric type such as <code>gauge</code> or <code>rate</code>.</p>\n</div>\n          </div>\n          \n        </div>\n      </div>\n      \n      <div class=\"row  \">\n        <div class=\"col-12 first-column\">\n          <div class=\"row first-row \">\n            \n    <div class=\"col-4 field-column\">\n      <p class=\"key\">unit</p>\n    </div>\n  \n            <div class=\"col-2 type-column\"><p>string</p></div>\n            <div class=\"col-6 description-column\"><p>Primary unit of the metric such as <code>byte</code> or <code>operation</code>.</p>\n</div>\n          </div>\n          \n        </div>\n      </div>\n      \n    </div>  \n  </div>"
    }
  },
  "QueryMetrics": {
    "responses": {
      "200": {
        "json": {
          "error": "string",
          "from_date": "integer",
          "group_by": "string",
          "message": "string",
          "query": "string",
          "res_type": "time_series",
          "series": {
            "aggr": "avg",
            "display_name": "system.cpu.idle",
            "end": "integer",
            "expression": "system.cpu.idle{host:foo,env:test}",
            "interval": "integer",
            "length": "integer",
            "metric": "system.cpu.idle",
            "pointlist": "number",
            "scope": "host:foo,env:test",
            "start": "integer",
            "unit": {
              "family": "time",
              "name": "minute",
              "plural": "minutes",
              "scale_factor": 60,
              "short_name": "min"
            }
          },
          "status": "ok",
          "to_date": "integer"
        },
        "html": "\n  <div class=\" schema-table row\">\n    <div class=\"col-12 column\">\n      <div class=\"row table-header\">\n        <div class=\"col-4 field-column\">\n          <p class=\"font-semibold\">Field</p>\n        </div>\n        <div class=\"col-2 type-column\">\n          <p class=\"font-semibold\">Type</p>\n        </div>\n        <div class=\"col-6 description-column\">\n          <p class=\"font-semibold\">Description</p>\n        </div>\n      </div>\n      \n      <div class=\"row  \">\n        <div class=\"col-12 first-column\">\n          <div class=\"row first-row \">\n            \n    <div class=\"col-4 field-column\">\n      <p class=\"key\">error</p>\n    </div>\n  \n            <div class=\"col-2 type-column\"><p>string <span class=\"read-only\">&#127361;</span></p></div>\n            <div class=\"col-6 description-column\"><p>Message indicating the errors if status is not <code>ok</code>.</p>\n</div>\n          </div>\n          \n        </div>\n      </div>\n      \n      <div class=\"row  \">\n        <div class=\"col-12 first-column\">\n          <div class=\"row first-row \">\n            \n    <div class=\"col-4 field-column\">\n      <p class=\"key\">from_date</p>\n    </div>\n  \n            <div class=\"col-2 type-column\"><p>int64 <span class=\"read-only\">&#127361;</span></p></div>\n            <div class=\"col-6 description-column\"><p>Start of requested time window, milliseconds since Unix epoch.</p>\n</div>\n          </div>\n          \n        </div>\n      </div>\n      \n      <div class=\"row  \">\n        <div class=\"col-12 first-column\">\n          <div class=\"row first-row \">\n            \n    <div class=\"col-4 field-column\">\n      <p class=\"key\">group_by</p>\n    </div>\n  \n            <div class=\"col-2 type-column\"><p>[string] <span class=\"read-only\">&#127361;</span></p></div>\n            <div class=\"col-6 description-column\"><p>List of tag keys on which to group.</p>\n</div>\n          </div>\n          \n        </div>\n      </div>\n      \n      <div class=\"row  \">\n        <div class=\"col-12 first-column\">\n          <div class=\"row first-row \">\n            \n    <div class=\"col-4 field-column\">\n      <p class=\"key\">message</p>\n    </div>\n  \n            <div class=\"col-2 type-column\"><p>string <span class=\"read-only\">&#127361;</span></p></div>\n            <div class=\"col-6 description-column\"><p>Message indicating <code>success</code> if status is <code>ok</code>.</p>\n</div>\n          </div>\n          \n        </div>\n      </div>\n      \n      <div class=\"row  \">\n        <div class=\"col-12 first-column\">\n          <div class=\"row first-row \">\n            \n    <div class=\"col-4 field-column\">\n      <p class=\"key\">query</p>\n    </div>\n  \n            <div class=\"col-2 type-column\"><p>string <span class=\"read-only\">&#127361;</span></p></div>\n            <div class=\"col-6 description-column\"><p>Query string</p>\n</div>\n          </div>\n          \n        </div>\n      </div>\n      \n      <div class=\"row  \">\n        <div class=\"col-12 first-column\">\n          <div class=\"row first-row \">\n            \n    <div class=\"col-4 field-column\">\n      <p class=\"key\">res_type</p>\n    </div>\n  \n            <div class=\"col-2 type-column\"><p>string <span class=\"read-only\">&#127361;</span></p></div>\n            <div class=\"col-6 description-column\"><p>Type of response.</p>\n</div>\n          </div>\n          \n        </div>\n      </div>\n      \n      <div class=\"row  hasChildData\">\n        <div class=\"col-12 first-column\">\n          <div class=\"row first-row js-collapse-trigger collapse-trigger\">\n            \n    <div class=\"col-4 field-column\">\n      <p class=\"key\"><span class=\"toggle-arrow\">></span> series</p>\n    </div>\n  \n            <div class=\"col-2 type-column\"><p>[object] <span class=\"read-only\">&#127361;</span></p></div>\n            <div class=\"col-6 description-column\"><p>List of timeseries queried.</p>\n</div>\n          </div>\n          \n      <div class=\"row isNested d-none \">\n        <div class=\"col-12 first-column\">\n          <div class=\"row first-row \">\n            \n    <div class=\"col-4 field-column\">\n      <p class=\"key\">aggr</p>\n    </div>\n  \n            <div class=\"col-2 type-column\"><p>string <span class=\"read-only\">&#127361;</span></p></div>\n            <div class=\"col-6 description-column\"><p>Aggregation type.</p>\n</div>\n          </div>\n          \n        </div>\n      </div>\n      \n      <div class=\"row isNested d-none \">\n        <div class=\"col-12 first-column\">\n          <div class=\"row first-row \">\n            \n    <div class=\"col-4 field-column\">\n      <p class=\"key\">display_name</p>\n    </div>\n  \n            <div class=\"col-2 type-column\"><p>string <span class=\"read-only\">&#127361;</span></p></div>\n            <div class=\"col-6 description-column\"><p>Display name of the metric.</p>\n</div>\n          </div>\n          \n        </div>\n      </div>\n      \n      <div class=\"row isNested d-none \">\n        <div class=\"col-12 first-column\">\n          <div class=\"row first-row \">\n            \n    <div class=\"col-4 field-column\">\n      <p class=\"key\">end</p>\n    </div>\n  \n            <div class=\"col-2 type-column\"><p>int64 <span class=\"read-only\">&#127361;</span></p></div>\n            <div class=\"col-6 description-column\"><p>End of the time window, milliseconds since Unix epoch.</p>\n</div>\n          </div>\n          \n        </div>\n      </div>\n      \n      <div class=\"row isNested d-none \">\n        <div class=\"col-12 first-column\">\n          <div class=\"row first-row \">\n            \n    <div class=\"col-4 field-column\">\n      <p class=\"key\">expression</p>\n    </div>\n  \n            <div class=\"col-2 type-column\"><p>string <span class=\"read-only\">&#127361;</span></p></div>\n            <div class=\"col-6 description-column\"><p>Metric expression.</p>\n</div>\n          </div>\n          \n        </div>\n      </div>\n      \n      <div class=\"row isNested d-none \">\n        <div class=\"col-12 first-column\">\n          <div class=\"row first-row \">\n            \n    <div class=\"col-4 field-column\">\n      <p class=\"key\">interval</p>\n    </div>\n  \n            <div class=\"col-2 type-column\"><p>int64 <span class=\"read-only\">&#127361;</span></p></div>\n            <div class=\"col-6 description-column\"><p>Number of seconds between data samples.</p>\n</div>\n          </div>\n          \n        </div>\n      </div>\n      \n      <div class=\"row isNested d-none \">\n        <div class=\"col-12 first-column\">\n          <div class=\"row first-row \">\n            \n    <div class=\"col-4 field-column\">\n      <p class=\"key\">length</p>\n    </div>\n  \n            <div class=\"col-2 type-column\"><p>int64 <span class=\"read-only\">&#127361;</span></p></div>\n            <div class=\"col-6 description-column\"><p>Number of data samples.</p>\n</div>\n          </div>\n          \n        </div>\n      </div>\n      \n      <div class=\"row isNested d-none \">\n        <div class=\"col-12 first-column\">\n          <div class=\"row first-row \">\n            \n    <div class=\"col-4 field-column\">\n      <p class=\"key\">metric</p>\n    </div>\n  \n            <div class=\"col-2 type-column\"><p>string <span class=\"read-only\">&#127361;</span></p></div>\n            <div class=\"col-6 description-column\"><p>Metric name.</p>\n</div>\n          </div>\n          \n        </div>\n      </div>\n      \n      <div class=\"row isNested d-none \">\n        <div class=\"col-12 first-column\">\n          <div class=\"row first-row \">\n            \n    <div class=\"col-4 field-column\">\n      <p class=\"key\">pointlist</p>\n    </div>\n  \n            <div class=\"col-2 type-column\"><p>[array] <span class=\"read-only\">&#127361;</span></p></div>\n            <div class=\"col-6 description-column\"><p>List of points of the time series.</p>\n</div>\n          </div>\n          \n        </div>\n      </div>\n      \n      <div class=\"row isNested d-none \">\n        <div class=\"col-12 first-column\">\n          <div class=\"row first-row \">\n            \n    <div class=\"col-4 field-column\">\n      <p class=\"key\">scope</p>\n    </div>\n  \n            <div class=\"col-2 type-column\"><p>string <span class=\"read-only\">&#127361;</span></p></div>\n            <div class=\"col-6 description-column\"><p>Metric scope, comma separated list of tags.</p>\n</div>\n          </div>\n          \n        </div>\n      </div>\n      \n      <div class=\"row isNested d-none \">\n        <div class=\"col-12 first-column\">\n          <div class=\"row first-row \">\n            \n    <div class=\"col-4 field-column\">\n      <p class=\"key\">start</p>\n    </div>\n  \n            <div class=\"col-2 type-column\"><p>int64 <span class=\"read-only\">&#127361;</span></p></div>\n            <div class=\"col-6 description-column\"><p>Start of the time window, milliseconds since Unix epoch.</p>\n</div>\n          </div>\n          \n        </div>\n      </div>\n      \n      <div class=\"row isNested d-none hasChildData\">\n        <div class=\"col-12 first-column\">\n          <div class=\"row first-row js-collapse-trigger collapse-trigger\">\n            \n    <div class=\"col-4 field-column\">\n      <p class=\"key\"><span class=\"toggle-arrow\">></span> unit</p>\n    </div>\n  \n            <div class=\"col-2 type-column\"><p>[object] <span class=\"read-only\">&#127361;</span></p></div>\n            <div class=\"col-6 description-column\"><p>Detailed information about the metric unit.\nFirst element describes the &quot;primary unit&quot; (for example, <code>bytes</code> in <code>bytes per second</code>),\nsecond describes the &quot;per unit&quot; (for example, <code>second</code> in <code>bytes per second</code>).</p>\n</div>\n          </div>\n          \n      <div class=\"row isNested d-none \">\n        <div class=\"col-12 first-column\">\n          <div class=\"row first-row \">\n            \n    <div class=\"col-4 field-column\">\n      <p class=\"key\">family</p>\n    </div>\n  \n            <div class=\"col-2 type-column\"><p>string <span class=\"read-only\">&#127361;</span></p></div>\n            <div class=\"col-6 description-column\"><p>Unit family, allows for conversion between units of the same family, for scaling.</p>\n</div>\n          </div>\n          \n        </div>\n      </div>\n      \n      <div class=\"row isNested d-none \">\n        <div class=\"col-12 first-column\">\n          <div class=\"row first-row \">\n            \n    <div class=\"col-4 field-column\">\n      <p class=\"key\">name</p>\n    </div>\n  \n            <div class=\"col-2 type-column\"><p>string <span class=\"read-only\">&#127361;</span></p></div>\n            <div class=\"col-6 description-column\"><p>Unit name</p>\n</div>\n          </div>\n          \n        </div>\n      </div>\n      \n      <div class=\"row isNested d-none \">\n        <div class=\"col-12 first-column\">\n          <div class=\"row first-row \">\n            \n    <div class=\"col-4 field-column\">\n      <p class=\"key\">plural</p>\n    </div>\n  \n            <div class=\"col-2 type-column\"><p>string <span class=\"read-only\">&#127361;</span></p></div>\n            <div class=\"col-6 description-column\"><p>Plural form of the unit name.</p>\n</div>\n          </div>\n          \n        </div>\n      </div>\n      \n      <div class=\"row isNested d-none \">\n        <div class=\"col-12 first-column\">\n          <div class=\"row first-row \">\n            \n    <div class=\"col-4 field-column\">\n      <p class=\"key\">scale_factor</p>\n    </div>\n  \n            <div class=\"col-2 type-column\"><p>double <span class=\"read-only\">&#127361;</span></p></div>\n            <div class=\"col-6 description-column\"><p>Factor for scaling between units of the same family.</p>\n</div>\n          </div>\n          \n        </div>\n      </div>\n      \n      <div class=\"row isNested d-none \">\n        <div class=\"col-12 first-column\">\n          <div class=\"row first-row \">\n            \n    <div class=\"col-4 field-column\">\n      <p class=\"key\">short_name</p>\n    </div>\n  \n            <div class=\"col-2 type-column\"><p>string <span class=\"read-only\">&#127361;</span></p></div>\n            <div class=\"col-6 description-column\"><p>Abbreviation of the unit.</p>\n</div>\n          </div>\n          \n        </div>\n      </div>\n      \n        </div>\n      </div>\n      \n        </div>\n      </div>\n      \n      <div class=\"row  \">\n        <div class=\"col-12 first-column\">\n          <div class=\"row first-row \">\n            \n    <div class=\"col-4 field-column\">\n      <p class=\"key\">status</p>\n    </div>\n  \n            <div class=\"col-2 type-column\"><p>string <span class=\"read-only\">&#127361;</span></p></div>\n            <div class=\"col-6 description-column\"><p>Status of the query.</p>\n</div>\n          </div>\n          \n        </div>\n      </div>\n      \n      <div class=\"row  \">\n        <div class=\"col-12 first-column\">\n          <div class=\"row first-row \">\n            \n    <div class=\"col-4 field-column\">\n      <p class=\"key\">to_date</p>\n    </div>\n  \n            <div class=\"col-2 type-column\"><p>int64 <span class=\"read-only\">&#127361;</span></p></div>\n            <div class=\"col-6 description-column\"><p>End of requested time window, milliseconds since Unix epoch.</p>\n</div>\n          </div>\n          \n        </div>\n      </div>\n      \n    </div>  \n  </div>"
      },
      "400": {
        "json": {
          "errors": "Bad Request"
        },
        "html": "\n  <div class=\" schema-table row\">\n    <div class=\"col-12 column\">\n      <div class=\"row table-header\">\n        <div class=\"col-4 field-column\">\n          <p class=\"font-semibold\">Field</p>\n        </div>\n        <div class=\"col-2 type-column\">\n          <p class=\"font-semibold\">Type</p>\n        </div>\n        <div class=\"col-6 description-column\">\n          <p class=\"font-semibold\">Description</p>\n        </div>\n      </div>\n      \n      <div class=\"row  \">\n        <div class=\"col-12 first-column\">\n          <div class=\"row first-row \">\n            \n    <div class=\"col-4 field-column\">\n      <p class=\"key\">errors<span style=\"color:red;\">*</span></p>\n    </div>\n  \n            <div class=\"col-2 type-column\"><p>[string]</p></div>\n            <div class=\"col-6 description-column\"></div>\n          </div>\n          \n        </div>\n      </div>\n      \n    </div>  \n  </div>"
      }
    },
    "request": {
      "json": {},
      "html": ""
    }
  },
  "ListMetrics": {
    "responses": {
      "200": {
        "json": {
          "results": "object"
        },
        "html": "\n  <div class=\" schema-table row\">\n    <div class=\"col-12 column\">\n      <div class=\"row table-header\">\n        <div class=\"col-4 field-column\">\n          <p class=\"font-semibold\">Field</p>\n        </div>\n        <div class=\"col-2 type-column\">\n          <p class=\"font-semibold\">Type</p>\n        </div>\n        <div class=\"col-6 description-column\">\n          <p class=\"font-semibold\">Description</p>\n        </div>\n      </div>\n      \n      <div class=\"row  hasChildData\">\n        <div class=\"col-12 first-column\">\n          <div class=\"row first-row js-collapse-trigger collapse-trigger\">\n            \n    <div class=\"col-4 field-column\">\n      <p class=\"key\"><span class=\"toggle-arrow\">></span> results</p>\n    </div>\n  \n            <div class=\"col-2 type-column\"><p>object</p></div>\n            <div class=\"col-6 description-column\"><p>Search result.</p>\n</div>\n          </div>\n          \n      <div class=\"row isNested d-none \">\n        <div class=\"col-12 first-column\">\n          <div class=\"row first-row \">\n            \n    <div class=\"col-4 field-column\">\n      <p class=\"key\">metrics</p>\n    </div>\n  \n            <div class=\"col-2 type-column\"><p>[string]</p></div>\n            <div class=\"col-6 description-column\"><p>List of metrics that match the search query.</p>\n</div>\n          </div>\n          \n        </div>\n      </div>\n      \n        </div>\n      </div>\n      \n    </div>  \n  </div>"
      },
      "400": {
        "json": {
          "errors": "Bad Request"
        },
        "html": "\n  <div class=\" schema-table row\">\n    <div class=\"col-12 column\">\n      <div class=\"row table-header\">\n        <div class=\"col-4 field-column\">\n          <p class=\"font-semibold\">Field</p>\n        </div>\n        <div class=\"col-2 type-column\">\n          <p class=\"font-semibold\">Type</p>\n        </div>\n        <div class=\"col-6 description-column\">\n          <p class=\"font-semibold\">Description</p>\n        </div>\n      </div>\n      \n      <div class=\"row  \">\n        <div class=\"col-12 first-column\">\n          <div class=\"row first-row \">\n            \n    <div class=\"col-4 field-column\">\n      <p class=\"key\">errors<span style=\"color:red;\">*</span></p>\n    </div>\n  \n            <div class=\"col-2 type-column\"><p>[string]</p></div>\n            <div class=\"col-6 description-column\"></div>\n          </div>\n          \n        </div>\n      </div>\n      \n    </div>  \n  </div>"
      },
      "500": {
        "json": {
          "errors": "Bad Request"
        },
        "html": "\n  <div class=\" schema-table row\">\n    <div class=\"col-12 column\">\n      <div class=\"row table-header\">\n        <div class=\"col-4 field-column\">\n          <p class=\"font-semibold\">Field</p>\n        </div>\n        <div class=\"col-2 type-column\">\n          <p class=\"font-semibold\">Type</p>\n        </div>\n        <div class=\"col-6 description-column\">\n          <p class=\"font-semibold\">Description</p>\n        </div>\n      </div>\n      \n      <div class=\"row  \">\n        <div class=\"col-12 first-column\">\n          <div class=\"row first-row \">\n            \n    <div class=\"col-4 field-column\">\n      <p class=\"key\">errors<span style=\"color:red;\">*</span></p>\n    </div>\n  \n            <div class=\"col-2 type-column\"><p>[string]</p></div>\n            <div class=\"col-6 description-column\"></div>\n          </div>\n          \n        </div>\n      </div>\n      \n    </div>  \n  </div>"
      }
    },
    "request": {
      "json": {},
      "html": ""
    }
  },
  "SubmitMetrics": {
    "responses": {
      "202": {
        "json": {
          "status": "ok"
        },
        "html": "\n  <div class=\" schema-table row\">\n    <div class=\"col-12 column\">\n      <div class=\"row table-header\">\n        <div class=\"col-4 field-column\">\n          <p class=\"font-semibold\">Field</p>\n        </div>\n        <div class=\"col-2 type-column\">\n          <p class=\"font-semibold\">Type</p>\n        </div>\n        <div class=\"col-6 description-column\">\n          <p class=\"font-semibold\">Description</p>\n        </div>\n      </div>\n      \n      <div class=\"row  \">\n        <div class=\"col-12 first-column\">\n          <div class=\"row first-row \">\n            \n    <div class=\"col-4 field-column\">\n      <p class=\"key\">status</p>\n    </div>\n  \n            <div class=\"col-2 type-column\"><p>string</p></div>\n            <div class=\"col-6 description-column\"></div>\n          </div>\n          \n        </div>\n      </div>\n      \n    </div>  \n  </div>"
      },
      "400": {
        "json": {
          "errors": "Bad Request"
        },
        "html": "\n  <div class=\" schema-table row\">\n    <div class=\"col-12 column\">\n      <div class=\"row table-header\">\n        <div class=\"col-4 field-column\">\n          <p class=\"font-semibold\">Field</p>\n        </div>\n        <div class=\"col-2 type-column\">\n          <p class=\"font-semibold\">Type</p>\n        </div>\n        <div class=\"col-6 description-column\">\n          <p class=\"font-semibold\">Description</p>\n        </div>\n      </div>\n      \n      <div class=\"row  \">\n        <div class=\"col-12 first-column\">\n          <div class=\"row first-row \">\n            \n    <div class=\"col-4 field-column\">\n      <p class=\"key\">errors<span style=\"color:red;\">*</span></p>\n    </div>\n  \n            <div class=\"col-2 type-column\"><p>[string]</p></div>\n            <div class=\"col-6 description-column\"></div>\n          </div>\n          \n        </div>\n      </div>\n      \n    </div>  \n  </div>"
      },
      "403": {
        "json": {
          "errors": "Bad Request"
        },
        "html": "\n  <div class=\" schema-table row\">\n    <div class=\"col-12 column\">\n      <div class=\"row table-header\">\n        <div class=\"col-4 field-column\">\n          <p class=\"font-semibold\">Field</p>\n        </div>\n        <div class=\"col-2 type-column\">\n          <p class=\"font-semibold\">Type</p>\n        </div>\n        <div class=\"col-6 description-column\">\n          <p class=\"font-semibold\">Description</p>\n        </div>\n      </div>\n      \n      <div class=\"row  \">\n        <div class=\"col-12 first-column\">\n          <div class=\"row first-row \">\n            \n    <div class=\"col-4 field-column\">\n      <p class=\"key\">errors<span style=\"color:red;\">*</span></p>\n    </div>\n  \n            <div class=\"col-2 type-column\"><p>[string]</p></div>\n            <div class=\"col-6 description-column\"></div>\n          </div>\n          \n        </div>\n      </div>\n      \n    </div>  \n  </div>"
      },
      "408": {
        "json": {
          "errors": "Bad Request"
        },
        "html": "\n  <div class=\" schema-table row\">\n    <div class=\"col-12 column\">\n      <div class=\"row table-header\">\n        <div class=\"col-4 field-column\">\n          <p class=\"font-semibold\">Field</p>\n        </div>\n        <div class=\"col-2 type-column\">\n          <p class=\"font-semibold\">Type</p>\n        </div>\n        <div class=\"col-6 description-column\">\n          <p class=\"font-semibold\">Description</p>\n        </div>\n      </div>\n      \n      <div class=\"row  \">\n        <div class=\"col-12 first-column\">\n          <div class=\"row first-row \">\n            \n    <div class=\"col-4 field-column\">\n      <p class=\"key\">errors<span style=\"color:red;\">*</span></p>\n    </div>\n  \n            <div class=\"col-2 type-column\"><p>[string]</p></div>\n            <div class=\"col-6 description-column\"></div>\n          </div>\n          \n        </div>\n      </div>\n      \n    </div>  \n  </div>"
      },
      "413": {
        "json": {
          "errors": "Bad Request"
        },
        "html": "\n  <div class=\" schema-table row\">\n    <div class=\"col-12 column\">\n      <div class=\"row table-header\">\n        <div class=\"col-4 field-column\">\n          <p class=\"font-semibold\">Field</p>\n        </div>\n        <div class=\"col-2 type-column\">\n          <p class=\"font-semibold\">Type</p>\n        </div>\n        <div class=\"col-6 description-column\">\n          <p class=\"font-semibold\">Description</p>\n        </div>\n      </div>\n      \n      <div class=\"row  \">\n        <div class=\"col-12 first-column\">\n          <div class=\"row first-row \">\n            \n    <div class=\"col-4 field-column\">\n      <p class=\"key\">errors<span style=\"color:red;\">*</span></p>\n    </div>\n  \n            <div class=\"col-2 type-column\"><p>[string]</p></div>\n            <div class=\"col-6 description-column\"></div>\n          </div>\n          \n        </div>\n      </div>\n      \n    </div>  \n  </div>"
      }
    },
    "request": {
      "json": {
        "series": {
          "host": "string",
          "interval": "integer",
          "metric": "system.load.1",
          "points": "number",
          "tags": "string",
          "type": "string"
        }
      },
      "html": "\n  <div class=\" schema-table row\">\n    <div class=\"col-12 column\">\n      <div class=\"row table-header\">\n        <div class=\"col-4 field-column\">\n          <p class=\"font-semibold\">Field</p>\n        </div>\n        <div class=\"col-2 type-column\">\n          <p class=\"font-semibold\">Type</p>\n        </div>\n        <div class=\"col-6 description-column\">\n          <p class=\"font-semibold\">Description</p>\n        </div>\n      </div>\n      \n      <div class=\"row  hasChildData\">\n        <div class=\"col-12 first-column\">\n          <div class=\"row first-row js-collapse-trigger collapse-trigger\">\n            \n    <div class=\"col-4 field-column\">\n      <p class=\"key\"><span class=\"toggle-arrow\">></span> series</p>\n    </div>\n  \n            <div class=\"col-2 type-column\"><p>[object]</p></div>\n            <div class=\"col-6 description-column\"><p>A list of time series to submit to Datadog.</p>\n</div>\n          </div>\n          \n      <div class=\"row isNested d-none \">\n        <div class=\"col-12 first-column\">\n          <div class=\"row first-row \">\n            \n    <div class=\"col-4 field-column\">\n      <p class=\"key\">host</p>\n    </div>\n  \n            <div class=\"col-2 type-column\"><p>string</p></div>\n            <div class=\"col-6 description-column\"><p>The name of the host that produced the metric.</p>\n</div>\n          </div>\n          \n        </div>\n      </div>\n      \n      <div class=\"row isNested d-none \">\n        <div class=\"col-12 first-column\">\n          <div class=\"row first-row \">\n            \n    <div class=\"col-4 field-column\">\n      <p class=\"key\">interval</p>\n    </div>\n  \n            <div class=\"col-2 type-column\"><p>int64</p></div>\n            <div class=\"col-6 description-column\"><p>If the type of the metric is rate or count, define the corresponding interval.</p>\n</div>\n          </div>\n          \n        </div>\n      </div>\n      \n      <div class=\"row isNested d-none \">\n        <div class=\"col-12 first-column\">\n          <div class=\"row first-row \">\n            \n    <div class=\"col-4 field-column\">\n      <p class=\"key\">metric</p>\n    </div>\n  \n            <div class=\"col-2 type-column\"><p>string</p></div>\n            <div class=\"col-6 description-column\"><p>The name of the timeseries.</p>\n</div>\n          </div>\n          \n        </div>\n      </div>\n      \n      <div class=\"row isNested d-none \">\n        <div class=\"col-12 first-column\">\n          <div class=\"row first-row \">\n            \n    <div class=\"col-4 field-column\">\n      <p class=\"key\">points</p>\n    </div>\n  \n            <div class=\"col-2 type-column\"><p>[array]</p></div>\n            <div class=\"col-6 description-column\"></div>\n          </div>\n          \n        </div>\n      </div>\n      \n      <div class=\"row isNested d-none \">\n        <div class=\"col-12 first-column\">\n          <div class=\"row first-row \">\n            \n    <div class=\"col-4 field-column\">\n      <p class=\"key\">tags</p>\n    </div>\n  \n            <div class=\"col-2 type-column\"><p>[string]</p></div>\n            <div class=\"col-6 description-column\"><p>A list of tags associated with the metric.</p>\n</div>\n          </div>\n          \n        </div>\n      </div>\n      \n      <div class=\"row isNested d-none \">\n        <div class=\"col-12 first-column\">\n          <div class=\"row first-row \">\n            \n    <div class=\"col-4 field-column\">\n      <p class=\"key\">type</p>\n    </div>\n  \n            <div class=\"col-2 type-column\"><p>string</p></div>\n            <div class=\"col-6 description-column\"></div>\n          </div>\n          \n        </div>\n      </div>\n      \n        </div>\n      </div>\n      \n    </div>  \n  </div>"
    }
  }
}