{
  "settings": {
    "minWordSizefor1Typo": 3,
    "minWordSizefor2Typos": 7,
    "hitsPerPage": 20,
    "maxValuesPerFacet": 100,
    "minProximity": 1,
    "attributesToIndex": [
      "unordered(hierarchy_radio_camel.lvl0)",
      "unordered(hierarchy_radio.lvl0)",
      "unordered(hierarchy_radio_camel.lvl1)",
      "unordered(hierarchy_radio.lvl1)",
      "unordered(hierarchy_radio_camel.lvl2)",
      "unordered(hierarchy_radio.lvl2)",
      "unordered(hierarchy_radio_camel.lvl3)",
      "unordered(hierarchy_radio.lvl3)",
      "unordered(hierarchy_radio_camel.lvl4)",
      "unordered(hierarchy_radio.lvl4)",
      "unordered(hierarchy_camel.lvl0)",
      "unordered(hierarchy.lvl0)",
      "unordered(hierarchy_camel.lvl1)",
      "unordered(hierarchy.lvl1)",
      "unordered(hierarchy_camel.lvl2)",
      "unordered(hierarchy.lvl2)",
      "unordered(hierarchy_camel.lvl3)",
      "unordered(hierarchy.lvl3)",
      "unordered(hierarchy_camel.lvl4)",
      "unordered(hierarchy.lvl4)",
      "content",
      "unordered(tags)"
    ],
    "numericAttributesToIndex": null,
    "attributesToRetrieve": [
      "anchor",
      "content",
      "hierarchy",
      "tags",
      "url"
    ],
    "allowTyposOnNumericTokens": false,
    "ignorePlurals": true,
    "camelCaseAttributes": [
      "hierarchy",
      "hierarchy_radio",
      "content"
    ],
    "advancedSyntax": true,
    "attributeCriteriaComputedByMinProximity": true,
    "distinct": true,
    "unretrievableAttributes": null,
    "optionalWords": [
      "the",
      "without"
    ],
    "userData": {
      "crawling_issue": false
    },
    "attributesForFaceting": [
      "language",
      "searchable(tags)"
    ],
    "attributesToSnippet": [
      "content:10"
    ],
    "attributesToHighlight": [
      "hierarchy",
      "hierarchy_camel",
      "content"
    ],
    "paginationLimitedTo": 1000,
    "attributeForDistinct": "url_without_anchor",
    "exactOnSingleWordQuery": "attribute",
    "ranking": [
      "words",
      "filters",
      "typo",
      "attribute",
      "proximity",
      "exact",
      "custom"
    ],
    "customRanking": [
      "asc(tags)",
      "desc(weight.page_rank)",
      "desc(weight.level)",
      "asc(weight.position)"
    ],
    "separatorsToIndex": "_@.",
    "removeWordsIfNoResults": "allOptional",
    "queryType": "prefixLast",
    "highlightPreTag": "<span class=\"algolia-docsearch-suggestion--highlight\">",
    "highlightPostTag": "</span>",
    "snippetEllipsisText": "",
    "alternativesAsExact": [
      "ignorePlurals",
      "singleWordSynonym"
    ]
  },
  "rules": [],
  "synonyms": [
    {
      "type": "synonym",
      "synonyms": [
        "RUM",
        "rum",
        "real user monitoring"
      ],
      "objectID": "_settings_syn_5"
    },
    {
      "type": "synonym",
      "synonyms": [
        "aws",
        "amazon web service"
      ],
      "objectID": "_settings_syn_4"
    },
    {
      "type": "synonym",
      "synonyms": [
        "gcp",
        "google cloud platform"
      ],
      "objectID": "_settings_syn_3"
    },
    {
      "type": "synonym",
      "synonyms": [
        "microsoft azure",
        "azure"
      ],
      "objectID": "_settings_syn_2"
    },
    {
      "type": "synonym",
      "synonyms": [
        "agent",
        "datadog agent"
      ],
      "objectID": "_settings_syn_1"
    }
  ]
}